instapy/__init__.py
instapy/download_reels.py
insta_scrape_py-0.0.50.dist-info/METADATA
insta_scrape_py-0.0.50.dist-info/WHEEL
insta_scrape_py-0.0.50.dist-info/top_level.txt
insta_scrape_py-0.0.50.dist-info/RECORD
