Metadata-Version: 2.4
Name: insta-scrape-py
Version: 0.0.50
Summary: A Python package to scrape and download Instagram Reels from any Instagram page.
Author: djalti
Author-email: abdeldjalilselamnia@gmail.com
Keywords: python,instagram,scrape,download,reels,pages
Classifier: Development Status :: 3 - Alpha
Classifier: Intended Audience :: Developers
Classifier: Programming Language :: Python :: 3
Classifier: Operating System :: Unix
Classifier: Operating System :: MacOS :: MacOS X
Classifier: Operating System :: Microsoft :: Windows
Requires-Dist: tqdm
Requires-Dist: requests
Dynamic: author
Dynamic: author-email
Dynamic: classifier
Dynamic: description
Dynamic: description-content-type
Dynamic: keywords
Dynamic: requires-dist
Dynamic: summary
